<?xml version="1.0" encoding="UTF-8"?>
<objects serializationModel="Studio.02.03.00">
	<object class="AudioFile" id="{c40d0a93-6822-416d-a0b0-42751ea54235}">
		<property name="assetPath">
			<value>Arrow Shot.mp3</value>
		</property>
		<property name="frequencyInKHz">
			<value>44.0999985</value>
		</property>
		<property name="channelCount">
			<value>2</value>
		</property>
		<property name="length">
			<value>0.60081632653061223</value>
		</property>
		<relationship name="masterAssetFolder">
			<destination>{ebd3a6d2-c20e-4b93-8949-f0d9802991d6}</destination>
		</relationship>
	</object>
</objects>
